{
  "$schema": "../schemas/golden-pages-schema.json",
  "version": "1.0.0",
  "lastUpdated": "2026-02-21T19:36:03.139Z",
  "pages": [
    {
      "id": "homepage",
      "url": "https://www.examplevenue.com",
      "title": "Example Venue | Beautiful Wedding Venue in City",
      "description": "Description from meta tags",
      "importance": "critical",
      "category": "about",
      "lastCrawled": "2026-02-21T10:00:00Z",
      "contentHash": "abc123def456",
      "extractedFacts": [
        "fact-home-001",
        "fact-home-002"
      ],
      "embeddingId": "emb-page-home"
    },
    {
      "id": "pricing",
      "url": "https://www.examplevenue.com/pricing",
      "title": "Wedding Packages & Pricing",
      "description": "Complete pricing information for wedding packages",
      "importance": "critical",
      "category": "pricing",
      "lastCrawled": "2026-02-21T10:05:00Z",
      "contentHash": "def456ghi789",
      "extractedFacts": [
        "fact-price-001",
        "fact-price-002",
        "fact-price-003"
      ],
      "embeddingId": "emb-page-pricing"
    },
    {
      "id": "venue-spaces",
      "url": "https://www.examplevenue.com/venues",
      "title": "Wedding Venues & Spaces",
      "description": "Explore our ceremony and reception spaces",
      "importance": "critical",
      "category": "venue",
      "lastCrawled": "2026-02-21T10:10:00Z",
      "contentHash": "ghi789jkl012",
      "extractedFacts": [
        "fact-venue-001",
        "fact-venue-002"
      ],
      "embeddingId": "emb-page-venues"
    },
    {
      "id": "accommodations",
      "url": "https://www.examplevenue.com/accommodations",
      "title": "Guest Accommodations",
      "description": "Information about guest lodging options",
      "importance": "high",
      "category": "accommodations",
      "lastCrawled": "2026-02-21T10:15:00Z",
      "contentHash": "jkl012mno345",
      "extractedFacts": [
        "fact-accom-001"
      ],
      "embeddingId": "emb-page-accom"
    },
    {
      "id": "faq",
      "url": "https://www.examplevenue.com/faq",
      "title": "Frequently Asked Questions",
      "description": "Answers to common wedding planning questions",
      "importance": "high",
      "category": "policies",
      "lastCrawled": "2026-02-21T10:20:00Z",
      "contentHash": "mno345pqr678",
      "extractedFacts": [
        "fact-faq-001",
        "fact-faq-002",
        "fact-faq-003"
      ],
      "embeddingId": "emb-page-faq"
    },
    {
      "id": "page-465c6c20",
      "url": "https://promise-farm.com",
      "title": "Promise Farm | Wedding Venue in Lancaster PA",
      "description": "Celebrate your day at Promise Farm, a peaceful 55-acre wedding venue in Lancaster County with flexible options and affordable pricing.",
      "importance": "critical",
      "category": "venue",
      "lastCrawled": "2026-02-21T19:31:28.968Z",
      "contentHash": "8329648bc599",
      "extractedFacts": [],
      "embeddingId": null,
      "imageUrls": [
        "https://promise-farm.com/wp-content/uploads/2025/09/logo.png",
        "https://promise-farm.com/wp-content/uploads/2025/11/Promise-Farm-Logo-500.png",
        "https://promise-farm.com/wp-content/uploads/2025/09/PF-Icon-75.png",
        "https://promise-farm.com/wp-content/uploads/2025/10/Arch.png",
        "https://promise-farm.com/wp-content/uploads/2025/10/Table.png",
        "https://promise-farm.com/wp-content/uploads/2025/10/Tray.png",
        "https://promise-farm.com/wp-content/uploads/2025/10/Map.png",
        "https://promise-farm.com/wp-content/uploads/2025/10/Camera.png",
        "https://promise-farm.com/wp-content/uploads/2025/10/Car.png",
        "https://promise-farm.com/wp-content/uploads/2025/09/gallery-01.jpg",
        "https://promise-farm.com/wp-content/uploads/2025/09/promisefarm-img-13.jpeg",
        "https://promise-farm.com/wp-content/uploads/2025/10/Promise-Farm-621.jpg",
        "https://promise-farm.com/wp-content/uploads/2025/10/Promise-Farm-617.jpg",
        "https://promise-farm.com/wp-content/uploads/2025/10/Promise-Farm-613.jpg",
        "https://promise-farm.com/wp-content/uploads/2025/11/Promise-Farm-715.jpg",
        "https://promise-farm.com/wp-content/uploads/2025/10/Promise-Farm-591.jpg",
        "https://promise-farm.com/wp-content/uploads/2025/10/Promise-Farm-547.jpg",
        "https://promise-farm.com/wp-content/uploads/2025/10/Promise-Farm-534.jpg",
        "https://promise-farm.com/wp-content/uploads/2025/10/Promise-Farm-503.jpg",
        "https://promise-farm.com/wp-content/uploads/2025/10/Promise-Farm-280.jpg"
      ],
      "textSample": "Promise Farm | Wedding Venue in Lancaster PA Home Weddings Events Gallery Reviews FAQs More Nearby Lodging Preferred Vendors Blog Contact Schedule a Tour Elegant and Affordable Wedding & Event Venue in the Heart of Lancaster County Wedding Venue in Lancaster, Pennsylvania A Beautiful and Spacious Setting, Ready for Your Story Promise Farm is where beautiful moments unfold in a setting that feels peaceful and down-to-earth. Our 55 acres of open farmland and rustic barn offer a lovely backdrop for saying “I do” surrounded by the people you love most. With flexible options and affordable pricing, you can plan a meaningful celebration that feels completely your own.  Air conditioned and heated barn, climate-controlled for year-round comfort  Outdoor ceremony area with sweeping countryside views  Space for up to 225 guests  Freedom to choose the vendors that fit your style and budget Learn More Schedule a Tour The Perfect Canvas for Your Wedding Day Beautiful Outdoor Ceremony Area Exchange your vows surrounded by open fields, a serene pond, and the quiet beauty of Lancaster County. Our outdoor ceremony space offers a peaceful, picture-worthy backdrop that feels naturally romantic. Spaceous Indoor Reception Space Celebrate with family and friends in a bright, open barn that feels both welcoming and relaxed. With heating and air conditioning, you can plan your day in any season and know your guests will feel right at home. Select the Caterer of Your Choice We believe in flexibility. Choose the caterer that fits your taste and budget, whether that means a formal plated dinner or your favorite local food truck. Promise Farm keeps it simple so your wedding can feel personal. Convenient Lancaster County Location Just minutes from town but surrounded by peaceful farmland, Promise Farm offers the best of both worlds. You will enjoy easy access for guests and a private, countryside feel. Flexibility in Choosing Your Favorite Vendors You’re welcome to choose the vendors that b"
    },
    {
      "id": "page-9847227c",
      "url": "https://promise-farm.com/feed",
      "title": "Promise Farm Wedding Venue",
      "description": "",
      "importance": "critical",
      "category": "pricing",
      "lastCrawled": "2026-02-21T19:31:28.972Z",
      "contentHash": "84c093394f6d",
      "extractedFacts": [],
      "embeddingId": null,
      "imageUrls": [
        "https://promise-farm.com/wp-content/uploads/2025/10/Promise-Farm-627-1024x683.jpg",
        "https://promise-farm.com/wp-content/uploads/2021/09/weddingvenuelancasterpa1.jpg",
        "https://promise-farm.com/wp-content/uploads/2025/10/Promise-Farm-595-1024x683.jpg",
        "https://promise-farm.com/wp-content/uploads/2021/11/Bridal-Suite-at-Promise-Farm.jpg",
        "https://promise-farm.com/wp-content/uploads/2023/06/LP-40.jpg",
        "https://promise-farm.com/wp-content/uploads/2021/08/Leah-Phillip-Wedding_552.jpg",
        "https://promise-farm.com/wp-content/uploads/2022/08/IMG_5401.jpeg",
        "https://promise-farm.com/wp-content/uploads/2022/08/IMG_5400.jpeg",
        "https://promise-farm.com/wp-content/uploads/2025/10/Promise-Farm-616-1024x683.jpg",
        "https://promise-farm.com/wp-content/uploads/2024/08/Vision-Lancaster-Wedding-Planning-Tips-1.jpg",
        "https://promise-farm.com/wp-content/uploads/2024/08/venue-Tour-Lancaster-Wedding-Planning-Tips.jpg",
        "https://promise-farm.com/wp-content/uploads/2026/01/PF-cocktail-hour-from-Freepik-1024x683.jpg",
        "https://promise-farm.com/wp-content/uploads/2021/09/weddingvenuelancasterpa5.jpg",
        "https://promise-farm.com/wp-content/uploads/2025/11/Promise-Farm-785-1024x683.jpg",
        "https://promise-farm.com/wp-content/uploads/2021/12/lancasterweddingvenue.jpg",
        "https://promise-farm.com/wp-content/uploads/2025/11/Promise-Farm-786-1024x683.jpg",
        "https://promise-farm.com/wp-content/uploads/2023/05/image6.jpeg"
      ],
      "textSample": "Promise Farm Wedding Venue https://promise-farm.com/ Mon, 16 Feb 2026 14:34:01 +0000 en-US hourly 1 https://wordpress.org/?v=6.9.1 https://promise-farm.com/wp-content/uploads/2025/11/cropped-Promise-Farm-Favicon-512-32x32.jpg Promise Farm Wedding Venue https://promise-farm.com/ 32 32 How to Plan a Rustic Wedding in Lancaster https://promise-farm.com/blog/how-to-plan-a-rustic-wedding-in-lancaster/ Mon, 16 Feb 2026 14:33:55 +0000 https://promisefarm.wpenginepowered.com/?p=3752 The post How to Plan a Rustic Wedding in Lancaster appeared first on Promise Farm Wedding Venue . ]]> Lancaster, PA, is a beautiful and serene location that perfectly captures the essence of rustic wedding charm. Promise Farm offers a cozy, intimate setting for couples who want a celebration that feels relaxed, personal, and true to them. With its picturesque 55-acre farm setting and flexible vendor policy, Promise Farm provides everything you need to create a memorable celebration. In this blog, we’ll guide you through planning the perfect country-inspired wedding in Lancaster, ensuring your big day is beautiful and stress-free. What's Involved in a Rustic Wedding Theme? A rustic wedding is characterized by its natural, simplistic elegance, often featuring organic materials, earthy colors, and a relaxed, inviting atmosphere. The key to a successful rustic wedding is blending the beauty of the natural surroundings with personal touches that reflect your style as a couple. Key Elements of a Rustic Wedding Natural Decor: Incorporate elements like wood, burlap, lace, and greenery. Earthy Color Palette: Use colors inspired by nature, such as soft greens, browns, and neutrals. Personal Touches: Include handmade or DIY elements to add a personal touch to your wedding decor. Promise Farm offers a homespun but elegant vibe that serves as a perfect backdrop for your wedding day. Our venue provides a blank canvas, allowing you to design your wedding exactly as you envision it. Learn more about our venue’s"
    },
    {
      "id": "page-cb237bc6",
      "url": "https://promise-farm.com/comments/feed",
      "title": "Comments for Promise Farm Wedding Venue",
      "description": "",
      "importance": "critical",
      "category": "pricing",
      "lastCrawled": "2026-02-21T19:31:28.974Z",
      "contentHash": "010b8dc0795a",
      "extractedFacts": [],
      "embeddingId": null,
      "imageUrls": [],
      "textSample": "Comments for Promise Farm Wedding Venue https://promise-farm.com/ Mon, 16 Feb 2026 16:25:39 +0000 hourly 1 https://wordpress.org/?v=6.9.1"
    },
    {
      "id": "page-c59cf2c4",
      "url": "https://promise-farm.com/wp-json",
      "title": "",
      "description": "",
      "importance": "critical",
      "category": "about",
      "lastCrawled": "2026-02-21T19:31:28.976Z",
      "contentHash": "d41d8cd98f00",
      "extractedFacts": [],
      "embeddingId": null,
      "imageUrls": [],
      "textSample": ""
    },
    {
      "id": "page-f0330325",
      "url": "https://promise-farm.com/wp-json/wp/v2/pages/243",
      "title": "",
      "description": "",
      "importance": "medium",
      "category": "other",
      "lastCrawled": "2026-02-21T19:31:28.977Z",
      "contentHash": "d41d8cd98f00",
      "extractedFacts": [],
      "embeddingId": null,
      "imageUrls": [],
      "textSample": ""
    },
    {
      "id": "page-7c4651c1",
      "url": "https://promise-farm.com/weddings",
      "title": "Lancaster County Wedding Venue | Promise Farm",
      "description": "Say “I do” surrounded by open fields and rustic charm. Promise Farm offers flexible vendor choices and space for up to 225 guests.",
      "importance": "critical",
      "category": "venue",
      "lastCrawled": "2026-02-21T19:31:28.978Z",
      "contentHash": "3bb38d583b19",
      "extractedFacts": [],
      "embeddingId": null,
      "imageUrls": [
        "https://promise-farm.com/wp-content/uploads/2025/09/logo.png",
        "https://promise-farm.com/wp-content/uploads/2025/09/PF-Icon-75.png",
        "https://promise-farm.com/wp-content/uploads/2025/10/Arch.png",
        "https://promise-farm.com/wp-content/uploads/2025/10/Hearts.png",
        "https://promise-farm.com/wp-content/uploads/2025/10/Camera.png",
        "https://promise-farm.com/wp-content/uploads/2025/10/RIng.png",
        "https://promise-farm.com/wp-content/uploads/2025/09/promisefarm-img-09.jpeg",
        "https://promise-farm.com/wp-content/uploads/2025/09/about-img-02.jpg",
        "https://promise-farm.com/wp-content/uploads/2025/09/promisefarm-82.jpeg",
        "https://promise-farm.com/wp-content/uploads/2025/10/Promise-Farm-591.jpg",
        "https://promise-farm.com/wp-content/uploads/2025/10/Promise-Farm-578.jpg",
        "https://promise-farm.com/wp-content/uploads/2025/10/Promise-Farm-537.jpg",
        "https://promise-farm.com/wp-content/uploads/2025/10/Promise-Farm-530.jpg",
        "https://promise-farm.com/wp-content/uploads/2025/11/Promise-Farm-714.jpg",
        "https://promise-farm.com/wp-content/uploads/2025/11/Promise-Farm-716.jpg",
        "https://promise-farm.com/wp-content/uploads/2025/10/Promise-Farm-101.jpg",
        "https://promise-farm.com/wp-content/uploads/2025/10/Promise-Farm-531.jpg"
      ],
      "textSample": "Lancaster County Wedding Venue | Promise Farm Home Weddings Events Gallery Reviews FAQs More Nearby Lodging Preferred Vendors Blog Contact Schedule a Tour Weddings at Promise Farm Romantic Weddings in Lancaster County, PA Modern Barn Weddings at Promise Farm Promise Farm sits quietly in the hills of Lancaster County, surrounded by open fields and the easy beauty of the countryside. It’s a place where couples can slow down, take in the view, and celebrate in a setting that feels welcoming and full of heart. From the first drive down our tree-lined lane to the last dance under the glow of the chandeliers, Promise Farm feels like a place made for moments you’ll never forget. Whether you’re planning something small or filling the room with all your favorite people, Promise Farm gives you the freedom to celebrate in your own way. Learn More Schedule a Tour Weddings at Promise Farm Promise Farm offers a simple, peaceful setting for your ceremony surrounded by the quiet beauty of Lancaster County. Whether you choose to exchange vows outdoors under the open sky or inside our modern barn, each space feels warm, welcoming, and filled with natural charm. Say “I Do” in a Beautiful Outdoor Setting Our ceremony lawn looks out over wide, open meadows with views that change beautifully through the seasons. It’s the perfect spot for couples who love the outdoors and want a relaxed, romantic atmosphere.  Expansive lawn with rolling hills and open skies  Beautiful light for sunset ceremonies or golden-hour photos  Flexible setup for arches, florals, or simple natural décor  Peaceful country sounds and fresh air — the perfect backdrop for your day The Heart of Your Celebration Our clean, modern barn offers the warmth and character that make Lancaster County weddings so special. It’s bright, comfortable, and ready to host both intimate gatherings and large celebrations.  Wood-beamed ceilings and soft, natural lighting  Climate-controlled for comfort in every season  Getting-ready"
    },
    {
      "id": "page-8bd67277",
      "url": "https://promise-farm.com/business-social-events",
      "title": "Event Venue in Lancaster PA | Promise Farm",
      "description": "Host business events, parties, or gatherings in a bright, comfortable barn with open farmland views and year-round climate control.",
      "importance": "critical",
      "category": "venue",
      "lastCrawled": "2026-02-21T19:31:28.979Z",
      "contentHash": "48a00e325983",
      "extractedFacts": [],
      "embeddingId": null,
      "imageUrls": [
        "https://promise-farm.com/wp-content/uploads/2025/09/logo.png",
        "https://promise-farm.com/wp-content/uploads/2025/09/PF-Icon-75.png",
        "https://promise-farm.com/wp-content/uploads/2025/10/Balloons.png",
        "https://promise-farm.com/wp-content/uploads/2025/10/Tray.png",
        "https://promise-farm.com/wp-content/uploads/2025/09/promisefarm-img-09.jpeg",
        "https://promise-farm.com/wp-content/uploads/2025/09/about-img-02.jpg",
        "https://promise-farm.com/wp-content/uploads/2025/09/promisefarm-82.jpeg",
        "https://promise-farm.com/wp-content/uploads/2025/10/Promise-Farm-113.jpg",
        "https://promise-farm.com/wp-content/uploads/2025/10/Promise-Farm-567.jpg",
        "https://promise-farm.com/wp-content/uploads/2025/10/Promise-Farm-288.jpg",
        "https://promise-farm.com/wp-content/uploads/2025/10/Promise-Farm-277.jpg",
        "https://promise-farm.com/wp-content/uploads/2025/10/Promise-Farm-576.jpg",
        "https://promise-farm.com/wp-content/uploads/2025/10/Promise-Farm-585.jpg"
      ],
      "textSample": "Event Venue in Lancaster PA | Promise Farm Home Weddings Events Gallery Reviews FAQs More Nearby Lodging Preferred Vendors Blog Contact Schedule a Tour Business & Social Events A Warm and Welcoming Space for Every Event Lancaster’s Premier Venue for Business and Social Events Promise Farm offers more than weddings. Set among the rolling hills of Lancaster County, our barn and outdoor spaces create a relaxed, inspiring atmosphere for gatherings that matter. The countryside setting provides a refreshing change from typical conference rooms and banquet halls. You get natural light, open air, and views that help people unwind and connect. Whether you're planning a corporate retreat, a milestone birthday, or an evening reception, the venue adapts to what you need without feeling generic or impersonal. Learn More Schedule a Tour Business & Social Events at Promise Farm Promise Farm offers a rustic yet refined atmosphere for gatherings of all kinds — from corporate events and networking receptions to milestone celebrations and private parties. Our spacious barn and surrounding grounds provide flexible layouts, year-round comfort, and an inviting ambiance that makes planning easy and ensures your guests feel right at home. Corporate Events in the Countryside Give your next meeting, banquet, or celebration a setting that stands out. Promise Farm combines rustic charm with modern convenience, offering inviting spaces that work beautifully for corporate receptions, company dinners, and networking events.  Wood-beamed ceilings and soft, natural lighting  Climate-controlled for comfort in every season  Expansive outdoor deck overlooking beautiful flower gardens  Perfect for parties, receptions, and celebrations. A Place for Parties & Celebrations Whether you’re hosting a birthday, anniversary, reunion, or shower, Promise Farm offers a welcoming atmosphere where guests instantly feel at ease. Its blend of rustic elegance and countryside serenity creates the perfect backdrop f"
    },
    {
      "id": "page-fb6d650a",
      "url": "https://promise-farm.com/gallery",
      "title": "Promise Farm Wedding Gallery",
      "description": "View photos of real weddings and celebrations at Promise Farm, a scenic barn venue surrounded by Lancaster’s rolling countryside.",
      "importance": "high",
      "category": "gallery",
      "lastCrawled": "2026-02-21T19:31:28.980Z",
      "contentHash": "52e8c0c312fb",
      "extractedFacts": [],
      "embeddingId": null,
      "imageUrls": [
        "https://promise-farm.com/wp-content/uploads/2025/09/logo.png",
        "https://promise-farm.com/wp-content/uploads/2025/09/PF-Icon-75.png",
        "https://promise-farm.com/wp-content/uploads/2025/09/about-img-02.jpg",
        "https://promise-farm.com/wp-content/uploads/2025/09/promisefarm-img-01.jpeg",
        "https://promise-farm.com/wp-content/uploads/2025/09/promisefarm-img-02.jpeg",
        "https://promise-farm.com/wp-content/uploads/2025/09/promisefarm-img-04.jpeg",
        "https://promise-farm.com/wp-content/uploads/2025/09/promisefarm-img-07.jpeg",
        "https://promise-farm.com/wp-content/uploads/2025/09/promisefarm-img-09.jpeg",
        "https://promise-farm.com/wp-content/uploads/2025/09/promisefarm-img-10.jpeg",
        "https://promise-farm.com/wp-content/uploads/2025/09/promisefarm-img-11.jpeg",
        "https://promise-farm.com/wp-content/uploads/2025/09/promisefarm-img-13.jpeg",
        "https://promise-farm.com/wp-content/uploads/2025/09/promisefarm-img-14.jpeg",
        "https://promise-farm.com/wp-content/uploads/2025/09/promisefarm-img-25.jpeg",
        "https://promise-farm.com/wp-content/uploads/2025/09/promisefarm-img-31.jpeg",
        "https://promise-farm.com/wp-content/uploads/2025/09/promisefarm-img-33.jpeg",
        "https://promise-farm.com/wp-content/uploads/2025/09/promisefarm-img-36.jpeg",
        "https://promise-farm.com/wp-content/uploads/2025/09/promisefarm-img-39.jpeg",
        "https://promise-farm.com/wp-content/uploads/2025/09/promisefarm-img-41.jpeg",
        "https://promise-farm.com/wp-content/uploads/2025/09/promisefarm-img-44.jpeg",
        "https://promise-farm.com/wp-content/uploads/2025/09/promisefarm-img-47.jpeg"
      ],
      "textSample": "Promise Farm Wedding Gallery Home Weddings Events Gallery Reviews FAQs More Nearby Lodging Preferred Vendors Blog Contact Schedule a Tour Gallery Gallery of Memories Made at Promise Farm Every celebration at Promise Farm is as unique and beautiful as the couples, families, and friends who gather here. From romantic wedding ceremonies and joyful receptions to special events filled with laughter and love, our venue provides a timeless backdrop for unforgettable moments. Browse the gallery below to see how Promise Farm’s rustic charm, scenic countryside, and inviting spaces come together to create picture-perfect memories. Filter images by category and click any image for a larger view All Ceremonies Couples Getting Ready Receptions Venue Wedding Party Prev 1 2 3 4 5 6 7 8 9 10 11 12 Next Learn More About Promise Farm CLICK to email us 717-368-4109 4753 Elizabethtown Road, Manheim, PA Browse Our Website Weddings Business & Social Events Gallery Testimonials Blog Follow Follow Follow Have you already scheduled your wedding at Promise Farm? Click HERE for our Client Resources Page Privacy Policy | Terms of Service Resources Schedule a Tour Contact FAQs Nearby Lodging Preferred Vendors ©2026 Promise Farm. All rights reserved. Website created with love by Team Wedding"
    },
    {
      "id": "page-57b30a8e",
      "url": "https://promise-farm.com/testimonials-reviews",
      "title": "Promise Farm Reviews | Lancaster PA Venue",
      "description": "Hear from couples who celebrated at Promise Farm and see why our Lancaster County venue is known for beauty, comfort, and value.",
      "importance": "critical",
      "category": "venue",
      "lastCrawled": "2026-02-21T19:31:28.981Z",
      "contentHash": "74ba3b14878a",
      "extractedFacts": [],
      "embeddingId": null,
      "imageUrls": [
        "https://promise-farm.com/wp-content/uploads/2025/09/logo.png",
        "https://promise-farm.com/wp-content/uploads/2025/09/PF-Icon-75.png",
        "https://promise-farm.com/wp-content/plugins/wp-social-reviews/assets/images/icon/icon-google.png",
        "https://promise-farm.com/wp-content/plugins/wp-social-reviews/assets/images/icon/icon-google-small.png",
        "https://promise-farm.com/wp-content/uploads/2025/09/promisefarm-img-09.jpeg",
        "https://promise-farm.com/wp-content/uploads/2025/09/about-img-02.jpg",
        "https://promise-farm.com/wp-content/uploads/2025/09/promisefarm-82.jpeg",
        "https://promise-farm.com/wp-content/uploads/2025/10/Promise-Farm-591.jpg"
      ],
      "textSample": "Promise Farm Reviews | Lancaster PA Venue Home Weddings Events Gallery Reviews FAQs More Nearby Lodging Preferred Vendors Blog Contact Schedule a Tour Reviews & Testimonials Kind Words from Our Couples Couples who have celebrated at Promise Farm often share how much they enjoyed their time here. Read their stories and see what they loved most about the venue, from the peaceful setting and easygoing atmosphere to the simple charm that makes every wedding feel special. See Google Reviews { Our wedding day was perfect! We cannot get over how beautiful everything turned out. We’re so thankful for Judy—her prompt responses, detailed contract, and her willingness to let us use whichever vendors fit our day. She lays everything out from the start, and it’s very easy to abide by her contract. We’re so blessed to have had our wedding here. We appreciate Judy and how she keeps the venue affordable so people like us can have our dream wedding! The property is always landscaped to perfection, which makes taking photos a breeze. The bridal suite is absolutely amazing and has ample space for all your ladies to get ready. The groom’s suite is also very nice and offers a pool table, among other options, to keep the men occupied. Our day-of coordinator, Kylie, was so helpful in keeping the day on track and answering any questions we had. She even fluffed my train before I walked down the aisle. If you’re thinking of getting married here—do it! This venue deserves way more than five stars. We will forever be grateful to Promise Farm for hosting our absolute dream wedding! - Samantha G (on The Knot) { We had our wedding at Promise Farm on May 3, 2024. To say that Promise Farm is a gorgeous wedding venue would be an understatement. We were lucky enough to have beautiful weather, so we held our ceremony outside and our reception inside the barn. The grounds are immaculately kept, the outdoor ceremony space is stunning, and the barn itself is spacious, clean, and climate-controlled. Afte"
    },
    {
      "id": "page-c41225d2",
      "url": "https://promise-farm.com/frequently-asked-questions",
      "title": "Wedding Venue FAQs | Promise Farm",
      "description": "Get answers about our wedding venue, pricing, and policies to help you plan your Lancaster County celebration with confidence.",
      "importance": "critical",
      "category": "venue",
      "lastCrawled": "2026-02-21T19:31:28.982Z",
      "contentHash": "61f399f4f0d0",
      "extractedFacts": [],
      "embeddingId": null,
      "imageUrls": [
        "https://promise-farm.com/wp-content/uploads/2025/09/logo.png",
        "https://promise-farm.com/wp-content/uploads/2025/09/PF-Icon-75.png",
        "https://promise-farm.com/wp-content/uploads/2025/09/promisefarm-img-09.jpeg",
        "https://promise-farm.com/wp-content/uploads/2025/09/about-img-02.jpg",
        "https://promise-farm.com/wp-content/uploads/2025/09/promisefarm-82.jpeg",
        "https://promise-farm.com/wp-content/uploads/2025/11/Promise-Farm-719.jpg"
      ],
      "textSample": "Wedding Venue FAQs | Promise Farm Home Weddings Events Gallery Reviews FAQs More Nearby Lodging Preferred Vendors Blog Contact Schedule a Tour Frequently Asked Questions Home FAQs Have Questions About Promise Farm? What’s included in the rental? When you book Promise Farm, you’ll receive access to the venue during your big day. This includes usage of all of our facilities, including the main room, bridal suite, groom changing area, and all 55-acres of outdoor areas including our pond and fountain, heart garden and parking. What’s included in the rental? When you book Promise Farm, you’ll receive access to the venue during your big day. This includes usage of all of our facilities, including the main room, bridal suite, groom changing area, and all 55-acres of outdoor areas including our pond and fountain, heart garden and parking. How many guests can your venue accommodate? Our venue comfortably accommodates up to 225 guests. How much is the deposit? 50% down non-refundable to secure dates, 50% 180 days prior. (See terms and conditions for additional information.) What are the hours that we can access the venue for our wedding? For Saturday and Sunday events, you may access the venue as early as 8am on the day of your event. For Friday events, you may also access the venue on the day before between 8am and 4pm. Is the venue climate controlled? Yes. Our barn is air-conditioned and heated so you can celebrate any time of year. Can I stop by to tour the venue? Absolutely! It’s the best way to see if Promise Farm is right for you. Fill out the contact form to schedule your visit. Are we allowed to use our own food and beverage vendors? Yes! We simply provide the space and it is up to you to choose the vendors you would like to assist for your wedding day. Is there parking available? Yes we have 100 parking spaces. Is the venue handicap accessible? Yes. It is handicap accessible. Learn More About Promise Farm CLICK to email us 717-368-4109 4753 Elizabethtown Road, Manhei"
    },
    {
      "id": "page-7cd4d522",
      "url": "https://promise-farm.com/nearby-lodging",
      "title": "Lancaster Wedding Lodging Near Promise Farm",
      "description": "Browse nearby hotels and inns for you and your guests when celebrating at Promise Farm in Lancaster County.",
      "importance": "high",
      "category": "accommodations",
      "lastCrawled": "2026-02-21T19:31:28.984Z",
      "contentHash": "cfb67bb697d5",
      "extractedFacts": [],
      "embeddingId": null,
      "imageUrls": [
        "https://promise-farm.com/wp-content/uploads/2025/09/logo.png",
        "https://promise-farm.com/wp-content/uploads/2025/09/PF-Icon-75.png",
        "https://promise-farm.com/wp-content/uploads/2025/09/promisefarm-img-09.jpeg",
        "https://promise-farm.com/wp-content/uploads/2025/09/about-img-02.jpg",
        "https://promise-farm.com/wp-content/uploads/2025/09/promisefarm-82.jpeg",
        "https://promise-farm.com/wp-content/uploads/2025/11/Promise-Farm-713.jpg"
      ],
      "textSample": "Lancaster Wedding Lodging Near Promise Farm Home Weddings Events Gallery Reviews FAQs More Nearby Lodging Preferred Vendors Blog Contact Schedule a Tour Nearby Lodging Nearby Hotels and Accommodations If you are planning a wedding or event at Promise Farm, there are plenty of comfortable places to stay close by. Guests can choose from charming inns, cozy bed and breakfasts, and trusted hotels just minutes from our Lancaster, Pennsylvania venue. Wherever you stay, you will find friendly hospitality and an easy drive to Promise Farm for a relaxed, stress-free visit. Manheim Manor B&B  3 miles  Website Country Vistas B&B  4 miles  Website Lancaster Inn & Suites  4 miles  Website Hampton Inn & Suites Mount Joy / Lancaster West  6 miles  Website Warehouse Hotel at The Nook  6 miles  Website Comfort Suites Manheim – Lancaster  6 miles  Website Holiday Inn Express & Suites Lancaster–Mount Joy  6 miles  Website The Wilbur Lititz – Tapestry Collection by Hilton  7 miles  Website Lititz Springs Inn & Spa  6 miles  Website Hotel Rock Lititz  8 miles  Website Homewood Suites by Hilton Lancaster  10 miles  Website Home2 Suites by Hilton Lancaster  10 miles  Website Residence Inn by Marriott Lancaster  11 miles  Website Cameron Estate Inn  13 miles  Website Tru by Hilton Lancaster East  14 miles  Website Learn More About Promise Farm CLICK to email us 717-368-4109 4753 Elizabethtown Road, Manheim, PA Browse Our Website Weddings Business & Social Events Gallery Testimonials Blog Follow Follow Follow Have you already scheduled your wedding at Promise Farm? Click HERE for our Client Resources Page Privacy Policy | Terms of Service Resources Schedule a Tour Contact FAQs Nearby Lodging Preferred Vendors ©2026 Promise Farm. All rights reserved. Website created with love by Team Wedding"
    },
    {
      "id": "page-80f40f6d",
      "url": "https://promise-farm.com/preferred-vendors",
      "title": "Lancaster Wedding Vendors | Promise Farm",
      "description": "Find trusted local vendors who know Promise Farm and can help bring your wedding or event vision to life with ease.",
      "importance": "critical",
      "category": "about",
      "lastCrawled": "2026-02-21T19:31:28.985Z",
      "contentHash": "63b44a3a3c2e",
      "extractedFacts": [],
      "embeddingId": null,
      "imageUrls": [
        "https://promise-farm.com/wp-content/uploads/2025/09/logo.png",
        "https://promise-farm.com/wp-content/uploads/2025/09/PF-Icon-75.png",
        "https://promise-farm.com/wp-content/uploads/2025/09/promisefarm-img-09.jpeg",
        "https://promise-farm.com/wp-content/uploads/2025/09/about-img-02.jpg",
        "https://promise-farm.com/wp-content/uploads/2025/09/promisefarm-82.jpeg",
        "https://promise-farm.com/wp-content/uploads/2025/10/Promise-Farm-578.jpg"
      ],
      "textSample": "Lancaster Wedding Vendors | Promise Farm Home Weddings Events Gallery Reviews FAQs More Nearby Lodging Preferred Vendors Blog Contact Schedule a Tour Preferred Vendors Recommended Wedding & Event Vendors Planning your event at Promise Farm is easier with our network of trusted local vendors. We've built relationships with florists, photographers, caterers, planners, and entertainment professionals who know the venue well. They understand how to work with the space and bring out its best qualities. Our preferred vendor list connects you with experienced people who can help shape a celebration that feels personal and runs smoothly. You're not starting from scratch, and that makes a difference. Tables and Chairs Tents For You Tents For You is the exclusive provider of tables and chairs for all events at Promise Farm. Their team knows our venue inside and out, ensuring that setup is seamless and every detail fits the space perfectly. As a trusted partner, they also offer special pricing for Promise Farm clients, making it easy and affordable to furnish your event beautifully. Call (717) 665-1300 Catering & Cakes Dutch Country Catering  Visit Website  [email&#160;protected]  (717) 664-0930 Two P's in a Pot  Visit Website  [email&#160;protected]  (717) 495-4198 Mission BBQ  Visit Website  [email&#160;protected]  (717) 801-1554 The Clay House  Visit Website  [email&#160;protected]  (717) 644-8214 Enck's Plus Catering  Visit Website  [email&#160;protected]  (717) 569-7000 Weddings By Hess Catering  Visit Website  [email&#160;protected]  (717) 464-3374 Rettew's Catering  Visit Website  [email&#160;protected]  (717) 665-9200 Simply From Scratch  Visit Website  [email&#160;protected]  (717) 299-1202 Stone Hill Catering  Visit Website  [email&#160;protected]  (717) 872-9136 Festive Board  Visit Website  [email&#160;protected]  (717) 854-2420 Nanalyn's Full-Filling Feasts  Visit Website  [email&#160;protected]  (717) 468-9943 Yoder's Catering  V"
    },
    {
      "id": "page-2427db79",
      "url": "https://promise-farm.com/blog",
      "title": "Promise Farm Blog | Wedding Tips & Stories",
      "description": "Read wedding inspiration, planning advice, and stories from real celebrations at Promise Farm in Lancaster County.",
      "importance": "medium",
      "category": "blog",
      "lastCrawled": "2026-02-21T19:31:28.985Z",
      "contentHash": "421423744e8f",
      "extractedFacts": [
        "fact-41ea0391",
        "fact-20d3551c",
        "fact-9c1fb732",
        "fact-7893ae13",
        "fact-8cda95d4",
        "fact-c1cc2cce",
        "fact-f6f0cfc2",
        "fact-dfa245f4"
      ],
      "embeddingId": null,
      "imageUrls": [
        "https://promise-farm.com/wp-content/uploads/2025/09/logo.png",
        "https://promise-farm.com/wp-content/uploads/2025/09/PF-Icon-75.png",
        "https://promise-farm.com/wp-content/uploads/2021/09/lancasterweddingreceptionhall5.jpg",
        "https://promise-farm.com/wp-content/uploads/2024/07/Bridal-Suite-Promise-Farm-.jpg",
        "https://promise-farm.com/wp-content/uploads/2025/10/Promise-Farm-547.jpg",
        "https://promise-farm.com/wp-content/uploads/2025/10/Promise-Farm-616.jpg",
        "https://promise-farm.com/wp-content/uploads/2026/01/PF-cocktail-hour-from-Freepik.jpg",
        "https://promise-farm.com/wp-content/uploads/2025/11/Promise-Farm-785.jpg",
        "https://promise-farm.com/wp-content/uploads/2021/12/promisefarmlancaster.jpg",
        "https://promise-farm.com/wp-content/uploads/2025/10/Promise-Farm-529.jpg",
        "https://promise-farm.com/wp-content/uploads/2021/09/weddingvenuelancasterpa2.jpg",
        "https://promise-farm.com/wp-content/uploads/2022/10/addie_eshelman_bdw-731_websize.jpg",
        "https://promise-farm.com/wp-content/uploads/2025/09/promisefarm-img-09.jpeg",
        "https://promise-farm.com/wp-content/uploads/2025/09/about-img-02.jpg",
        "https://promise-farm.com/wp-content/uploads/2025/09/promisefarm-82.jpeg",
        "https://promise-farm.com/wp-content/uploads/2025/11/Promise-Farm-714.jpg"
      ],
      "textSample": "Promise Farm Blog | Wedding Tips & Stories Home Weddings Events Gallery Reviews FAQs More Nearby Lodging Preferred Vendors Blog Contact Schedule a Tour Promise Farm Blog Real Weddings and Unique Ideas Find ideas, real wedding stories, and helpful planning tips from couples who celebrated at Promise Farm. Whether you’re dreaming up décor, exploring vendor options, or just looking for inspiration, our blog is here to help you plan a day that feels personal and full of heart. How to Plan a Rustic Wedding in Lancaster Lancaster, PA, is a beautiful and serene location that perfectly captures the essence of rustic wedding charm. Promise Farm offers a cozy, intimate setting for couples who want a celebration that feels relaxed, personal, and true to them. With its picturesque 55-acre&#8230; Read More Inside the Promise Farm Bridal Suite: Getting Ready Space for Lancaster Weddings Planning a wedding is an exciting but often stressful experience. One of the key elements to consider when selecting your wedding venue is the bridal suite. At Promise Farm, located in the beautiful countryside of Lancaster, PA, we offer an exceptional bridal suite&#8230; Read More Best Wedding Photoshoot Ideas in Lancaster | Promise Farm Capturing your wedding day through stunning photos is a must for every couple. Lancaster, with its picturesque landscapes and charming venues, offers a plethora of opportunities for beautiful wedding photoshoots. At Promise Farm, we provide an idyllic setting that&#8230; Read More Lancaster Wedding Planning Tips Planning a wedding is an exciting yet challenging journey, especially when aiming to create a memorable day that reflects your unique love story. As one of Lancaster’s premier wedding venues, Promise Farm is here to guide you through the process with our expert tips&#8230; Read More 5 Tips to Plan the Perfect Cocktail Hour in Lancaster Planning a wedding or special event involves countless details, each contributing to the overall success and enjoyment of"
    },
    {
      "id": "page-ce2eed09",
      "url": "https://promise-farm.com/contact",
      "title": "Contact Promise Farm | Lancaster Wedding Venue",
      "description": "Get in touch with Promise Farm to ask questions or schedule a tour of our Lancaster County wedding and event venue.",
      "importance": "critical",
      "category": "venue",
      "lastCrawled": "2026-02-21T19:31:28.986Z",
      "contentHash": "35bea08cc0c9",
      "extractedFacts": [],
      "embeddingId": null,
      "imageUrls": [
        "https://promise-farm.com/wp-content/uploads/2025/09/logo.png",
        "https://promise-farm.com/wp-content/uploads/2025/09/PF-Icon-75.png",
        "https://promise-farm.com/wp-content/uploads/2025/10/Promise-Farm-621.jpg"
      ],
      "textSample": "Contact Promise Farm | Lancaster Wedding Venue Home Weddings Events Gallery Reviews FAQs More Nearby Lodging Preferred Vendors Blog Contact Schedule a Tour Contact Us Home Contact Connect With Promise Farm  Address 4753 Elizabethtown Road Manheim, PA 17545  Email Us CLICK to email us  Call Us 717-368-4109 CLICK to email us 717-368-4109 4753 Elizabethtown Road, Manheim, PA Browse Our Website Weddings Business & Social Events Gallery Testimonials Blog Follow Follow Follow Have you already scheduled your wedding at Promise Farm? Click HERE for our Client Resources Page Privacy Policy | Terms of Service Resources Schedule a Tour Contact FAQs Nearby Lodging Preferred Vendors ©2026 Promise Farm. All rights reserved. Website created with love by Team Wedding"
    },
    {
      "id": "page-b95fbb56",
      "url": "https://promise-farm.com/schedule-a-tour",
      "title": "Tour Promise Farm Wedding Venue",
      "description": "Schedule a private tour of Promise Farm in Lancaster County and see why couples love our relaxed setting and flexible options.",
      "importance": "critical",
      "category": "venue",
      "lastCrawled": "2026-02-21T19:31:28.987Z",
      "contentHash": "276ae3c322e6",
      "extractedFacts": [],
      "embeddingId": null,
      "imageUrls": [
        "https://promise-farm.com/wp-content/uploads/2025/09/logo.png",
        "https://promise-farm.com/wp-content/uploads/2025/09/PF-Icon-75.png",
        "https://promise-farm.com/wp-content/uploads/2025/10/Promise-Farm-621.jpg"
      ],
      "textSample": "Tour Promise Farm Wedding Venue Home Weddings Events Gallery Reviews FAQs More Nearby Lodging Preferred Vendors Blog Contact Schedule a Tour Schedule a Tour Schedule a Tour of Promise Farm Schedule a visit to Promise Farm and see why couples throughout Lancaster County love celebrating here. Walk through the barn, explore the ceremony spaces, and picture your day surrounded by open fields and peaceful views. Our affordable rates, flexible vendor policy, and year-round comfort make planning your wedding simple and enjoyable. Top-Rated Wedding Venue in Lancaster County Promise Farm is loved by couples who want a beautiful, relaxed place to celebrate surrounded by Lancaster’s rolling farmland. Our venue combines open space, comfort, and flexibility, making it easy to plan a day that feels personal and genuine. With affordable pricing and plenty of room for up to 225 guests, Promise Farm offers everything you need for a memorable wedding. Located just outside Manheim, we’re close to major roads, hotels, and local attractions, making travel simple for you and your guests. Come see why so many couples choose Promise Farm as the best value in Lancaster County. CLICK to email us 717-368-4109 4753 Elizabethtown Road, Manheim, PA Browse Our Website Weddings Business & Social Events Gallery Testimonials Blog Follow Follow Follow Have you already scheduled your wedding at Promise Farm? Click HERE for our Client Resources Page Privacy Policy | Terms of Service Resources Schedule a Tour Contact FAQs Nearby Lodging Preferred Vendors ©2026 Promise Farm. All rights reserved. Website created with love by Team Wedding"
    },
    {
      "id": "page-c14f7ba3",
      "url": "https://promise-farm.com/blog/how-to-plan-a-rustic-wedding-in-lancaster",
      "title": "How to Plan a Rustic Wedding in Lancaster | Promise Farm",
      "description": "Plan your rustic wedding at Promise Farm in Lancaster with tips on venue selection, décor, & incorporating local charm for a memorable day.",
      "importance": "medium",
      "category": "blog",
      "lastCrawled": "2026-02-21T19:31:28.988Z",
      "contentHash": "a8343f68dee7",
      "extractedFacts": [
        "fact-113e1e04",
        "fact-44f7f559",
        "fact-968ae83d",
        "fact-fd1bda79",
        "fact-684206f9",
        "fact-6465193d",
        "fact-f449e781"
      ],
      "embeddingId": null,
      "imageUrls": [
        "https://promise-farm.com/wp-content/uploads/2025/09/logo.png",
        "https://promise-farm.com/wp-content/uploads/2025/10/Promise-Farm-627-1024x683.jpg",
        "https://promise-farm.com/wp-content/uploads/2021/09/weddingvenuelancasterpa1.jpg",
        "https://promise-farm.com/wp-content/uploads/2021/09/lancasterweddingreceptionhall5.jpg"
      ],
      "textSample": "How to Plan a Rustic Wedding in Lancaster | Promise Farm Home Weddings Events Gallery Reviews FAQs More Nearby Lodging Preferred Vendors Blog Contact Schedule a Tour How to Plan a Rustic Wedding in Lancaster Home Blog How to Plan a Rustic Wedding in Lancaster Lancaster, PA, is a beautiful and serene location that perfectly captures the essence of rustic wedding charm. Promise Farm offers a cozy, intimate setting for couples who want a celebration that feels relaxed, personal, and true to them. With its picturesque 55-acre farm setting and flexible vendor policy, Promise Farm provides everything you need to create a memorable celebration. In this blog, we’ll guide you through planning the perfect country-inspired wedding in Lancaster, ensuring your big day is beautiful and stress-free. What's Involved in a Rustic Wedding Theme? A rustic wedding is characterized by its natural, simplistic elegance, often featuring organic materials, earthy colors, and a relaxed, inviting atmosphere. The key to a successful rustic wedding is blending the beauty of the natural surroundings with personal touches that reflect your style as a couple. Key Elements of a Rustic Wedding Natural Decor: Incorporate elements like wood, burlap, lace, and greenery. Earthy Color Palette: Use colors inspired by nature, such as soft greens, browns, and neutrals. Personal Touches: Include handmade or DIY elements to add a personal touch to your wedding decor. Promise Farm offers a homespun but elegant vibe that serves as a perfect backdrop for your wedding day. Our venue provides a blank canvas, allowing you to design your wedding exactly as you envision it. Learn more about our venue’s rustic charm and how it can enhance your wedding theme. How Do I Choose the Right Wedding Venue? Selecting the right venue is crucial for creating the perfect rustic wedding. The venue sets the tone for the entire event, so it’s important to choose a location that aligns with your theme. Considerations When Choosing a R"
    },
    {
      "id": "page-5f31deaf",
      "url": "https://promise-farm.com/blog/best-bridal-suite-at-promise-farm-in-lancaster",
      "title": "Best Bridal Suite at Promise Farm in Lancaster",
      "description": "Explore the best bridal suite at Promise Farm in Lancaster. Experience comfort, elegance & privacy on your wedding day. Schedule a tour today.",
      "importance": "high",
      "category": "accommodations",
      "lastCrawled": "2026-02-21T19:31:28.990Z",
      "contentHash": "c267df86873e",
      "extractedFacts": [],
      "embeddingId": null,
      "imageUrls": [
        "https://promise-farm.com/wp-content/uploads/2025/09/logo.png",
        "https://promise-farm.com/wp-content/uploads/2025/10/Promise-Farm-595-1024x683.jpg",
        "https://promise-farm.com/wp-content/uploads/2021/11/Bridal-Suite-at-Promise-Farm.jpg",
        "https://promise-farm.com/wp-content/uploads/2024/07/Bridal-Suite-Promise-Farm-.jpg"
      ],
      "textSample": "Best Bridal Suite at Promise Farm in Lancaster Home Weddings Events Gallery Reviews FAQs More Nearby Lodging Preferred Vendors Blog Contact Schedule a Tour Inside the Promise Farm Bridal Suite: Getting Ready Space for Lancaster Weddings Home Blog Inside the Promise Farm Bridal Suite: Getting Ready Space for Lancaster Weddings Planning a wedding is an exciting but often stressful experience. One of the key elements to consider when selecting your wedding venue is the bridal suite. At Promise Farm, located in the beautiful countryside of Lancaster, PA, we offer an exceptional bridal suite that ensures a memorable and stress-free wedding day. In this blog post, we'll explore the best features of our bridal suite, provide helpful tips, and share testimonials from brides who have experienced the magic of Promise Farm . What Makes a Bridal Suite Worth It? A bridal suite is more than just a room to get ready in. It’s a sanctuary where the bride and her bridal party can relax, prepare, and share special moments before the ceremony. A well-appointed bridal suite can set the tone for the entire day, providing comfort, convenience, and a touch of luxury. Key Benefits of a Great Bridal Suite Comfortable Space: A spacious and well-furnished area where the bride and her party can comfortably prepare. Privacy: A private space away from the hustle and bustle of the wedding preparations. Photo Opportunities: A beautiful setting for those special pre-wedding photos. Relaxation : A place to unwind and calm any pre-wedding nerves. Features of the Bridal Suite at Promise Farm Promise Farm's bridal suite is designed with the bride's comfort and convenience in mind. Here are some of the standout features that make our bridal suite the best in Lancaster: Bridal Suite Amenities That Make Getting Ready Easier The suite is equipped with modern amenities, including air conditioning and heating, ensuring a comfortable stay in any season. There is also a private outdoor deck, offering a serene s"
    },
    {
      "id": "page-f1ac0205",
      "url": "https://promise-farm.com/blog/wedding-photoshoot-ideas-in-lancaster",
      "title": "Best Wedding Photoshoot Ideas in Lancaster | Promise Farm",
      "description": "Discover top wedding photoshoot ideas in Lancaster at Promise Farm, the premier barn wedding venue with stunning backdrops.",
      "importance": "high",
      "category": "gallery",
      "lastCrawled": "2026-02-21T19:31:28.992Z",
      "contentHash": "741398883a7d",
      "extractedFacts": [],
      "embeddingId": null,
      "imageUrls": [
        "https://promise-farm.com/wp-content/uploads/2025/09/logo.png",
        "https://promise-farm.com/wp-content/uploads/2023/06/LP-40.jpg",
        "https://promise-farm.com/wp-content/uploads/2021/08/Leah-Phillip-Wedding_552.jpg",
        "https://promise-farm.com/wp-content/uploads/2022/08/IMG_5401.jpeg",
        "https://promise-farm.com/wp-content/uploads/2022/08/IMG_5400.jpeg",
        "https://promise-farm.com/wp-content/uploads/2025/10/Promise-Farm-547.jpg"
      ],
      "textSample": "Best Wedding Photoshoot Ideas in Lancaster | Promise Farm Home Weddings Events Gallery Reviews FAQs More Nearby Lodging Preferred Vendors Blog Contact Schedule a Tour Best Wedding Photoshoot Ideas in Lancaster | Promise Farm Home Blog Best Wedding Photoshoot Ideas in Lancaster | Promise Farm Capturing your wedding day through stunning photos is a must for every couple. Lancaster, with its picturesque landscapes and charming venues, offers a plethora of opportunities for beautiful wedding photoshoots. At Promise Farm , we provide an idyllic setting that perfectly blends rustic charm with elegant backdrops. Here’s a guide to the best wedding photoshoot ideas in Lancaster, ensuring your memories are both beautiful and timeless. Plan Beautiful Barn Wedding Photos at Promise Farm Lancaster is renowned for its beautiful barns, and Promise Farm is no exception. Our rustic barn offers a perfect backdrop for your wedding photos, combining the natural beauty of aged wood with elegant decor. The barn’s structure provides a warm and intimate setting, ideal for capturing those precious moments. Helpful Tips Decorate the barn with fairy lights and rustic props for a magical ambiance. Visit our gallery to see how other couples have used our barn for their wedding photos. Use the barn doors, beams, and entryways as natural framing for portraits. Step just outside the barn for a wide shot with the farm in the background, then come back in for close-up portraits. Where to Take the Best Outdoor Wedding Photos The 55-acre farm setting at Promise Farm offers endless opportunities to incorporate nature into your wedding photos. From lush green fields to serene ponds, the natural elements provide a stunning and ever-changing backdrop. Helpful Tips Plan a photoshoot by the pond for a serene and romantic setting. Capture moments under large, shady trees for a whimsical touch. Use the edges of the fields for wide, open shots that show the Lancaster countryside. Take a short walk for a privat"
    },
    {
      "id": "page-d5de8fa7",
      "url": "https://promise-farm.com/client-info",
      "title": "Promise Farm Venue Layout & Capacity",
      "description": "View Promise Farm’s barn layout and ceremony spaces to plan your event flow and seating for up to 225 guests.",
      "importance": "critical",
      "category": "venue",
      "lastCrawled": "2026-02-21T19:31:28.995Z",
      "contentHash": "7294ba7dc093",
      "extractedFacts": [],
      "embeddingId": null,
      "imageUrls": [
        "https://promise-farm.com/wp-content/uploads/2025/09/logo.png",
        "https://promise-farm.com/wp-content/uploads/2025/09/PF-Icon-75.png",
        "https://promise-farm.com/wp-content/uploads/2025/11/225-Round-Rectangular-FP.jpg",
        "https://promise-farm.com/wp-content/uploads/2025/11/225-Rectangular-FP.jpg",
        "https://promise-farm.com/wp-content/uploads/2025/11/200-Round-Rectangular-FP.jpg",
        "https://promise-farm.com/wp-content/uploads/2025/11/200-Rectangular-FP.jpg",
        "https://promise-farm.com/wp-content/uploads/2025/11/175-Round-Rectangular-FP.jpg",
        "https://promise-farm.com/wp-content/uploads/2025/11/175-Round-FP.jpg",
        "https://promise-farm.com/wp-content/uploads/2025/11/175-Rectangular-FP.jpg",
        "https://promise-farm.com/wp-content/uploads/2025/11/150-Round-Rectangular-FP.jpg",
        "https://promise-farm.com/wp-content/uploads/2025/11/150-Round-FP.jpg",
        "https://promise-farm.com/wp-content/uploads/2025/11/125-Round-Rectangular-FP.jpg",
        "https://promise-farm.com/wp-content/uploads/2025/11/125-Round-FP.jpg",
        "https://promise-farm.com/wp-content/uploads/2025/11/100-Round-FP.jpg",
        "https://promise-farm.com/wp-content/uploads/2025/11/75-Round-FP-2.jpg",
        "https://promise-farm.com/wp-content/uploads/2025/09/promisefarm-img-09.jpeg",
        "https://promise-farm.com/wp-content/uploads/2025/09/about-img-02.jpg",
        "https://promise-farm.com/wp-content/uploads/2025/09/promisefarm-82.jpeg",
        "https://promise-farm.com/wp-content/uploads/2025/10/Promise-Farm-607.jpg"
      ],
      "textSample": "Promise Farm Venue Layout & Capacity Home Weddings Events Gallery Reviews FAQs More Nearby Lodging Preferred Vendors Blog Contact Schedule a Tour Wedding Information for Clients We're Looking Forward to Your Big Day! Welcome to the Promise Farm client resource page, your go-to spot for all the details you’ll need as you plan your wedding day. Here, you’ll find helpful tools like our event information form, sample floor plans, and a link to our recommended vendor list to make your planning process smooth and stress-free. Wedding Info Form Floor Plans Insurance Recommended Vendors Wedding Information Form Please submit this form at least 30 days prior to your wedding. Your rental includes 5 1/2 hours of event time from start to finish, and your event must end by 9:30 pm. You may arrive as early as 8 am and you must vacate the venue by 11 pm. \" * \" indicates required fields Your Contact Information Name * First Last Email * Your Cell Number * Wedding Date * MM slash DD slash YYYY Guest Count * Day-Of Contacts Who would you like to be our key contact for the day? * Cell Phone * Who is responsible for removal of trash and personal items? * Cell Phone * Vendor Contact Information DJ/Musicians Name DJ/Musicians Phone DJ/Musicians Email DJ/Musicians IG Handle (for tagging) Photographer Name Photographer Phone Photographer Email Photographer IG Handle (for tagging) Videographer Name Videographer Phone Videographer Email Videographer IG Handle (for tagging) Caterer Name Caterer Phone Caterer Email Caterer IG Handle (for tagging) Florist Name Florist Phone Florist Email Florist IG Handle (for tagging) Hair/Make Up Name Hair/Make Up Phone Hair/Make Up Email Hair/Makeup IG Handle (for tagging) Cake Baker Name Cake Baker Phone Cake Baker Email Cake Baker IG Handle (for tagging) Rentals Name Rentals Phone Rentals Email Rentals IG Handle (for tagging) Vendor Arrival Times Setup Begins/Rentals Arrive Hair/Make Up Artists Arrive Photographer Arrives Caterer Arrives Florist/Decorator "
    },
    {
      "id": "page-24e2cc61",
      "url": "https://promise-farm.com/privacy-policy",
      "title": "Privacy Policy | Promise Farm Wedding Venue",
      "description": "Promise Farm cares about your online privacy. Our privacy policy page outlines the data we collect and the steps we take to protect it.",
      "importance": "critical",
      "category": "venue",
      "lastCrawled": "2026-02-21T19:31:28.996Z",
      "contentHash": "a8c8e8a0e62d",
      "extractedFacts": [],
      "embeddingId": null,
      "imageUrls": [
        "https://promise-farm.com/wp-content/uploads/2025/09/logo.png",
        "https://promise-farm.com/wp-content/uploads/2025/09/promisefarm-img-09.jpeg",
        "https://promise-farm.com/wp-content/uploads/2025/09/about-img-02.jpg",
        "https://promise-farm.com/wp-content/uploads/2025/09/promisefarm-82.jpeg",
        "https://promise-farm.com/wp-content/uploads/2025/11/cropped-Promise-Farm-Favicon-512.jpg"
      ],
      "textSample": "Privacy Policy | Promise Farm Wedding Venue Home Weddings Events Gallery Reviews FAQs More Nearby Lodging Preferred Vendors Blog Contact Schedule a Tour Privacy Policy Promise Farm Privacy Policy Effective Date: September 1, 2021 Last Updated: November 8, 2025 This Privacy Policy (“Policy”) applies to promise-farm.com and Promise Farm (“Company,” “we,” “us,” or “our”) and explains how we collect, use, disclose, and protect your personal information. By using our website or services, you consent to the practices described in this Policy. 1. Collection of Personal Information We collect personal information you voluntarily provide to us to deliver the products and services you request. This may include: First and last name Email address Phone number We may also collect additional information when you register for an account, participate in promotions, send us a message, or make a purchase. We do not collect personal information without your consent. However, some features or services may not be available if you choose not to provide the requested information. 2. Use of Personal Information We use the information we collect to: Provide and deliver the services you request Respond to inquiries and provide customer support Process payments and fulfill transactions Send you updates, confirmations, and account notices Communicate about products, services, and promotions that may interest you Notify you of policy or service changes Comply with legal obligations and enforce our rights We may also use your information in other ways consistent with the purpose for which it was collected, or with your consent. 3. Email and SMS Messaging Consent By submitting your contact information through our website, web application, or contact forms, you expressly consent to receive communications from us via email and SMS (text messaging) . These may include: Transactional Messages: Reservation confirmations, reminders, and service updates. Customer Support Messages: Responses to inquiries"
    },
    {
      "id": "page-c0bdb7c9",
      "url": "https://promise-farm.com/terms-of-service",
      "title": "Terms of Service | Promise Farm Wedding Venue",
      "description": "Our terms of service page outlines what you can expect when visiting our website and working with Promise Farm.",
      "importance": "critical",
      "category": "venue",
      "lastCrawled": "2026-02-21T19:31:28.997Z",
      "contentHash": "2233d971d357",
      "extractedFacts": [],
      "embeddingId": null,
      "imageUrls": [
        "https://promise-farm.com/wp-content/uploads/2025/09/logo.png",
        "https://promise-farm.com/wp-content/uploads/2025/09/promisefarm-img-09.jpeg",
        "https://promise-farm.com/wp-content/uploads/2025/09/about-img-02.jpg",
        "https://promise-farm.com/wp-content/uploads/2025/09/promisefarm-82.jpeg",
        "https://promise-farm.com/wp-content/uploads/2025/11/cropped-Promise-Farm-Favicon-512.jpg"
      ],
      "textSample": "Terms of Service | Promise Farm Wedding Venue Home Weddings Events Gallery Reviews FAQs More Nearby Lodging Preferred Vendors Blog Contact Schedule a Tour Terms of Service Terms of Service Effective Date: September 6, 2025 Promise Farm https://promise-farm.com By accessing this website or booking any services offered by Promise Farm (“Company,” “we,” “our,” or “us”), you (“Client,” “Guest,” “User,” or “you”) agree to be bound by the following Terms of Service . Please read these terms carefully before making reservations or using our services. 1. Services Provided Promise Farm provides: Event and wedding venue rentals Event coordination and planning support Access to venue-related amenities, packages, and promotional offerings All services are provided in accordance with Pennsylvania state laws and the policies outlined in these Terms. 2. Client Responsibilities By booking with Promise Farm, you agree to: Provide accurate and current information during all inquiries and reservations Comply with all property policies, including event schedules, capacity limits, and conduct rules Obtain any required permits or approvals for event activities when applicable Be responsible for any damages to the property, facilities, or equipment caused by you, your guests, or your vendors Pay all fees, deposits, and balances according to agreed-upon terms Failure to comply with these responsibilities may result in additional charges or cancellation of your event or reservation. 3. Payment & Cancellation Payment: All reservations must be secured with a valid payment method at the time of booking. Specific payment terms and due dates are outlined in your event contract or invoice. Deposits: Certain reservations, including weddings and private events, require deposits or prepayments. Deposit amounts and schedules will be specified in your contract. Cancellations: Cancellation policies vary depending on the type of event or service. Cancellations outside of contracted terms may result in f"
    },
    {
      "id": "page-3cec416e",
      "url": "https://promise-farm.com/venue-tour",
      "title": "Tour Promise Farm Wedding Venue",
      "description": "Schedule a private tour of Promise Farm in Lancaster County and see why couples love our relaxed setting and flexible options.",
      "importance": "critical",
      "category": "venue",
      "lastCrawled": "2026-02-21T19:31:28.998Z",
      "contentHash": "276ae3c322e6",
      "extractedFacts": [],
      "embeddingId": null,
      "imageUrls": [
        "https://promise-farm.com/wp-content/uploads/2025/09/logo.png",
        "https://promise-farm.com/wp-content/uploads/2025/09/PF-Icon-75.png",
        "https://promise-farm.com/wp-content/uploads/2025/10/Promise-Farm-621.jpg"
      ],
      "textSample": "Tour Promise Farm Wedding Venue Home Weddings Events Gallery Reviews FAQs More Nearby Lodging Preferred Vendors Blog Contact Schedule a Tour Schedule a Tour Schedule a Tour of Promise Farm Schedule a visit to Promise Farm and see why couples throughout Lancaster County love celebrating here. Walk through the barn, explore the ceremony spaces, and picture your day surrounded by open fields and peaceful views. Our affordable rates, flexible vendor policy, and year-round comfort make planning your wedding simple and enjoyable. Top-Rated Wedding Venue in Lancaster County Promise Farm is loved by couples who want a beautiful, relaxed place to celebrate surrounded by Lancaster’s rolling farmland. Our venue combines open space, comfort, and flexibility, making it easy to plan a day that feels personal and genuine. With affordable pricing and plenty of room for up to 225 guests, Promise Farm offers everything you need for a memorable wedding. Located just outside Manheim, we’re close to major roads, hotels, and local attractions, making travel simple for you and your guests. Come see why so many couples choose Promise Farm as the best value in Lancaster County. CLICK to email us 717-368-4109 4753 Elizabethtown Road, Manheim, PA Browse Our Website Weddings Business & Social Events Gallery Testimonials Blog Follow Follow Follow Have you already scheduled your wedding at Promise Farm? Click HERE for our Client Resources Page Privacy Policy | Terms of Service Resources Schedule a Tour Contact FAQs Nearby Lodging Preferred Vendors ©2026 Promise Farm. All rights reserved. Website created with love by Team Wedding"
    },
    {
      "id": "page-7476b89f",
      "url": "https://promise-farm.com/contact-us",
      "title": "Contact Promise Farm | Lancaster Wedding Venue",
      "description": "Get in touch with Promise Farm to ask questions or schedule a tour of our Lancaster County wedding and event venue.",
      "importance": "critical",
      "category": "venue",
      "lastCrawled": "2026-02-21T19:31:29.000Z",
      "contentHash": "35bea08cc0c9",
      "extractedFacts": [],
      "embeddingId": null,
      "imageUrls": [
        "https://promise-farm.com/wp-content/uploads/2025/09/logo.png",
        "https://promise-farm.com/wp-content/uploads/2025/09/PF-Icon-75.png",
        "https://promise-farm.com/wp-content/uploads/2025/10/Promise-Farm-621.jpg"
      ],
      "textSample": "Contact Promise Farm | Lancaster Wedding Venue Home Weddings Events Gallery Reviews FAQs More Nearby Lodging Preferred Vendors Blog Contact Schedule a Tour Contact Us Home Contact Connect With Promise Farm  Address 4753 Elizabethtown Road Manheim, PA 17545  Email Us CLICK to email us  Call Us 717-368-4109 CLICK to email us 717-368-4109 4753 Elizabethtown Road, Manheim, PA Browse Our Website Weddings Business & Social Events Gallery Testimonials Blog Follow Follow Follow Have you already scheduled your wedding at Promise Farm? Click HERE for our Client Resources Page Privacy Policy | Terms of Service Resources Schedule a Tour Contact FAQs Nearby Lodging Preferred Vendors ©2026 Promise Farm. All rights reserved. Website created with love by Team Wedding"
    },
    {
      "id": "page-de8ff476",
      "url": "https://promise-farm.com/how-to-choose-a-wedding-venue-tips-and-tricks-for-finding-the-perfect-location/).",
      "title": "Wedding Venue Selection : Tips and Tricks | Promise Farm Wedding Venue",
      "description": "Learn how to choose the perfect wedding venue at Promise Farm in Lancaster. Discover tips and tricks for finding your dream location.",
      "importance": "critical",
      "category": "venue",
      "lastCrawled": "2026-02-21T19:31:29.001Z",
      "contentHash": "dc5598fd9412",
      "extractedFacts": [],
      "embeddingId": null,
      "imageUrls": [
        "https://promise-farm.com/wp-content/uploads/2025/09/logo.png",
        "https://promise-farm.com/wp-content/uploads/2021/09/weddingvenueinlancaster.jpg"
      ],
      "textSample": "Wedding Venue Selection : Tips and Tricks | Promise Farm Wedding Venue Home Weddings Events Gallery Reviews FAQs More Nearby Lodging Preferred Vendors Blog Contact Schedule a Tour How To Choose A Wedding Venue: Tips And Tricks For Finding The Perfect Location Home Wedding How To Choose A Wedding Venue: Tips And Tricks For Finding The Perfect Location Planning a wedding can be stressful. From choosing the perfect dress to deciding your guest list, there are many decisions that need to be made before the big day arrives. One of the most important decisions you will make is selecting a venue for your wedding ceremony and reception. The venue will be one of the most memorable decisions you make, so it&#8217;s worth taking to find the right one for you and your partner. In this blog post we&#8217;ll explore 11 tips and tricks for finding a perfect location! #1 Find Out if Your Date is Available &#8211; As you&#8217;re shopping for wedding venues, it&#8217;s important to have a date in mind for your wedding. So as you&#8217;re reaching out to potential wedding venues make sure to ask if your date is available. If you&#8217;re flexible on which day of the week to get married, you may consider doing it on a Friday or Sunday. Some venues provide discounted rental rates, so make sure to ask about our Friday and Sunday rates. #2 Schedule a Venue Tour &#8211; The best way to know if the venue is right for you is to plan a visit with your partner. Before the tour, write down any questions you may have, and plan some time during your visit to review them with the venue. Also as you tour the venue, make sure to keep an open mind. It&#8217;s possible the venue may not be decorated, so try to visualize it dressed to the nine&#8217;s with all your wedding day decor. #3 Take Pictures and Video &#8211; During your tour, make sure to take pictures and video of the venue and decide the best location for perfect wedding and engagement photoshoot . You can always refer to them during the w"
    },
    {
      "id": "page-91287958",
      "url": "https://promise-farm.com/blog/lancaster-wedding-planning-tips",
      "title": "Lancaster Wedding Planning Tips | Promise Farm Guide",
      "description": "Plan your perfect Lancaster wedding with tips from Promise Farm. Discover expert advice on venue selection, seasonal planning, and more.",
      "importance": "medium",
      "category": "blog",
      "lastCrawled": "2026-02-21T19:31:29.002Z",
      "contentHash": "624dcdbafa1f",
      "extractedFacts": [
        "fact-94183e6e",
        "fact-032d5d48",
        "fact-b6cdd3e7",
        "fact-8ae70610",
        "fact-4ced0857",
        "fact-f4662a17",
        "fact-564fba46",
        "fact-4bec0d2c",
        "fact-d20c05c5"
      ],
      "embeddingId": null,
      "imageUrls": [
        "https://promise-farm.com/wp-content/uploads/2025/09/logo.png",
        "https://promise-farm.com/wp-content/uploads/2025/10/Promise-Farm-616-1024x683.jpg",
        "https://promise-farm.com/wp-content/uploads/2024/08/Vision-Lancaster-Wedding-Planning-Tips-1.jpg",
        "https://promise-farm.com/wp-content/uploads/2024/08/venue-Tour-Lancaster-Wedding-Planning-Tips.jpg",
        "https://promise-farm.com/wp-content/uploads/2025/10/Promise-Farm-616.jpg"
      ],
      "textSample": "Lancaster Wedding Planning Tips | Promise Farm Guide Home Weddings Events Gallery Reviews FAQs More Nearby Lodging Preferred Vendors Blog Contact Schedule a Tour Lancaster Wedding Planning Tips Home Blog Lancaster Wedding Planning Tips Planning a wedding is an exciting yet challenging journey, especially when aiming to create a memorable day that reflects your unique love story. As one of Lancaster’s premier wedding venues, Promise Farm is here to guide you through the process with our expert tips and local insights. These tips will help you plan your wedding with ease and confidence, ensuring your big day is everything you’ve dreamed of and more. 1. How to Start Planning Your Wedding Day Before diving into the planning, it's essential to have a clear vision of your wedding. Consider the overall theme, colors, and style you want to incorporate. Are you dreaming of a rustic barn wedding or an elegant garden ceremony? At Promise Farm, we offer a rustic elegant vibe, providing a versatile space that allows couples to decorate it to their heart’s content. 2. Pick the Perfect Wedding Venue Selecting the perfect venue is one of the most critical decisions you'll make. Here are some tips and questions to ask to help you choose the best setting for your special day: Check Venue Availability Ensure your preferred date is available. Flexibility on the day of the week can sometimes lead to discounted rates. Promise Farm offers special rates for Friday and Sunday weddings. Learn more about our affordable venue pricing . Arrange a Venue Tour Schedule a tour of potential venues. At Promise Farm, we encourage couples to visit and see our 55-acre farm setting and rustic barn in person. Take pictures and videos during your tour to help visualize your wedding day. Does Your Wedding Style Match the Venue? Choose a venue that fits the overall feel you want for your wedding day. Our spacious main room, outdoor deck, and scenic grounds offer a variety of settings to match any style. 3. D"
    },
    {
      "id": "page-49d273aa",
      "url": "https://promise-farm.com/blog/5-tips-to-plan-the-perfect-cocktail-hour-in-lancaster",
      "title": "Tips to Plan the Perfect Cocktail Hour in Lancaster | Promise Farm",
      "description": "Plan perfect cocktail hour at Promise Farm with tips on venue selection, drinks, appetizers, décor & entertainment to enhance your event",
      "importance": "medium",
      "category": "blog",
      "lastCrawled": "2026-02-21T19:31:29.003Z",
      "contentHash": "b3dbd00af97f",
      "extractedFacts": [
        "fact-f91ab24f",
        "fact-94183e6e",
        "fact-d6e96901",
        "fact-5a8b0e46",
        "fact-6ab66a27",
        "fact-aa665558"
      ],
      "embeddingId": null,
      "imageUrls": [
        "https://promise-farm.com/wp-content/uploads/2025/09/logo.png",
        "https://promise-farm.com/wp-content/uploads/2026/01/PF-cocktail-hour-from-Freepik-1024x683.jpg",
        "https://promise-farm.com/wp-content/uploads/2021/09/weddingvenuelancasterpa5.jpg",
        "https://promise-farm.com/wp-content/uploads/2026/01/PF-cocktail-hour-from-Freepik.jpg"
      ],
      "textSample": "Tips to Plan the Perfect Cocktail Hour in Lancaster | Promise Farm Home Weddings Events Gallery Reviews FAQs More Nearby Lodging Preferred Vendors Blog Contact Schedule a Tour 5 Tips to Plan the Perfect Cocktail Hour in Lancaster Home Blog 5 Tips to Plan the Perfect Cocktail Hour in Lancaster Planning a wedding or special event involves countless details, each contributing to the overall success and enjoyment of the day. One aspect that often stands out for guests is the cocktail hour: a time to relax, mingle, and enjoy delicious drinks and appetizers before the main event. In this blog post, we'll provide expert tips on how to plan an unforgettable cocktail hour, with a special focus on hosting it at Promise Farm, Lancaster's premier event venue. Why Is a Cocktail Hour Important for Guests? The cocktail hour is more than just a prelude to the reception; it's a vital part of your event that sets the tone for the rest of the evening. It offers guests a chance to socialize, enjoy refreshments, and transition easily from the ceremony to the celebration. What Are the Benefits of a Well-Planned Cocktail Hour? Socializing : Provides guests with an opportunity to catch up and mingle before the formalities begin. Atmosphere : Sets the mood with music, décor, and lighting that align with the theme of your event. Refreshments : Offers guests a selection of beverages and appetizers to enjoy, ensuring they're comfortable and content. Photography Time : Allows the couple or host to take photos or handle other tasks while guests are entertained. How Do You Plan a Cocktail Hour? Planning a cocktail hour involves several important decisions, from selecting the right location to choosing the perfect menu. Here are some key considerations to keep in mind: 1. How Do You Choose the Right Cocktail Hour Venue? Choosing the right venue is crucial for a successful cocktail hour. Promise Farm in Lancaster offers a variety of indoor and outdoor spaces that are perfect for hosting a cocktail "
    },
    {
      "id": "page-a8315887",
      "url": "https://promise-farm.com/blog/wedding-reception-tips-to-for-your-dream-day",
      "title": "Wedding Reception Tips for Your Dream Day | Promise Farm",
      "description": "Perfect wedding reception at Promise Farm in Lancaster with tips on choosing right venue, décor, entertainment, catering & event for dream day",
      "importance": "critical",
      "category": "venue",
      "lastCrawled": "2026-02-21T19:31:29.005Z",
      "contentHash": "6ee19dedbfc3",
      "extractedFacts": [],
      "embeddingId": null,
      "imageUrls": [
        "https://promise-farm.com/wp-content/uploads/2025/09/logo.png",
        "https://promise-farm.com/wp-content/uploads/2025/11/Promise-Farm-785-1024x683.jpg",
        "https://promise-farm.com/wp-content/uploads/2021/12/lancasterweddingvenue.jpg",
        "https://promise-farm.com/wp-content/uploads/2025/11/Promise-Farm-785.jpg"
      ],
      "textSample": "Wedding Reception Tips for Your Dream Day | Promise Farm Home Weddings Events Gallery Reviews FAQs More Nearby Lodging Preferred Vendors Blog Contact Schedule a Tour Tips to Make Your Wedding Reception a Dream Come True Home Blog Tips to Make Your Wedding Reception a Dream Come True Your wedding reception is more than just a celebration; it’s the culmination of your love story, the moment where friends and family come together to celebrate your union. Planning the perfect wedding reception can be both exciting and daunting, but with the right tips and guidance, you can create a day that truly reflects your dreams. At Promise Farm, we’re dedicated to helping couples bring their visions to life. In this blog post, we’ll share essential tips to ensure your wedding reception is everything you’ve ever dreamed of. 1. How Do You Define the Style and Feel of Your Wedding Reception? The first step in planning your dream wedding reception is to start with a clear vision. What do you want your reception to feel like? Whether you’re envisioning a rustic, elegant affair or a modern, chic celebration, having a well-defined vision will guide all your planning decisions. Key Questions to Define Your Vision What is the overall theme or style of your wedding? What emotions do you want your guests to experience? How do you want to incorporate personal elements into your reception? At Promise Farm, our versatile venue serves as a blank canvas, allowing you to create a reception that perfectly aligns with your vision. Learn more about our venue’s unique offerings and how they can be tailored to your dream wedding. 2. How Do You Choose the Right Wedding Reception Venue? Selecting the right venue is one of the most critical decisions you’ll make when planning your wedding reception. The venue sets the tone for your event and plays a significant role in the overall experience for you and your guests. What Should You Look for When Selecting a Wedding Reception Venue? Location: Ensure the ve"
    },
    {
      "id": "page-58183e86",
      "url": "https://promise-farm.com/blog/things-guests-know-before-your-wedding",
      "title": "Things Your Guests Need to Know Before Your Wedding in Lancaster",
      "description": "Things your guests need to know before your wedding in Lancaster, including venue details, accommodations, dress code, & local attractions.",
      "importance": "medium",
      "category": "blog",
      "lastCrawled": "2026-02-21T19:31:29.006Z",
      "contentHash": "48000fe06181",
      "extractedFacts": [],
      "embeddingId": null,
      "imageUrls": [
        "https://promise-farm.com/wp-content/uploads/2025/09/logo.png",
        "https://promise-farm.com/wp-content/uploads/2025/11/Promise-Farm-786-1024x683.jpg",
        "https://promise-farm.com/wp-content/uploads/2023/05/image6.jpeg",
        "https://promise-farm.com/wp-content/uploads/2021/12/promisefarmlancaster.jpg"
      ],
      "textSample": "Things Your Guests Need to Know Before Your Wedding in Lancaster Home Weddings Events Gallery Reviews FAQs More Nearby Lodging Preferred Vendors Blog Contact Schedule a Tour Things Your Guests Need to Know Before Your Wedding in Lancaster Home Blog Things Your Guests Need to Know Before Your Wedding in Lancaster Planning a wedding involves numerous details, and one of the most important aspects is ensuring that your guests have all the information they need to enjoy your big day. Lancaster, PA, is a beautiful location with its rustic charm and serene landscapes, making it an ideal spot for a wedding. Read on to help your guests have a seamless and enjoyable experience. There are a few key things they should know before attending your wedding at Promise Farm. 1. Where is Promise Farm? The first thing your guests need to know is how to get to your wedding venue. Promise Farm is located in the heart of Lancaster County, offering a picturesque setting that embodies rustic elegance. Directions to Promise Farm Address : 4753 Elizabethtown Road, Manheim, PA 17545, United States GPS Coordinates: Ensure your guests have the correct address entered into their GPS to avoid any confusion. It’s also helpful to include nearby landmarks in your invitations or wedding website. Parking: Promise Farm offers ample parking facilities, making it easy for guests to arrive and depart without hassle. For detailed directions and more information about the venue, you can visit our venue tour page . 2. Where Can We Stay Overnight in Lancaster? Lancaster has a variety of accommodation options for guests traveling from out of town. Whether your guests prefer a quaint bed and breakfast, a modern hotel, or a cozy Airbnb, there’s something for everyone. Recommended Accommodation Options Hotels: Lancaster Marriott at Penn Square and Eden Resort & Suites are popular choices offering modern amenities and comfort. Bed and Breakfasts: The Lancaster Bed & Breakfast and The Inn at Leola Village offer cha"
    },
    {
      "id": "page-e96fb4cd",
      "url": "https://promise-farm.com/how-to-choose-a-wedding-venue-tips-and-tricks-for-finding-the-perfect-location",
      "title": "Wedding Venue Selection : Tips and Tricks | Promise Farm Wedding Venue",
      "description": "Learn how to choose the perfect wedding venue at Promise Farm in Lancaster. Discover tips and tricks for finding your dream location.",
      "importance": "critical",
      "category": "venue",
      "lastCrawled": "2026-02-21T19:31:29.007Z",
      "contentHash": "dc5598fd9412",
      "extractedFacts": [],
      "embeddingId": null,
      "imageUrls": [
        "https://promise-farm.com/wp-content/uploads/2025/09/logo.png",
        "https://promise-farm.com/wp-content/uploads/2021/09/weddingvenueinlancaster.jpg"
      ],
      "textSample": "Wedding Venue Selection : Tips and Tricks | Promise Farm Wedding Venue Home Weddings Events Gallery Reviews FAQs More Nearby Lodging Preferred Vendors Blog Contact Schedule a Tour How To Choose A Wedding Venue: Tips And Tricks For Finding The Perfect Location Home Wedding How To Choose A Wedding Venue: Tips And Tricks For Finding The Perfect Location Planning a wedding can be stressful. From choosing the perfect dress to deciding your guest list, there are many decisions that need to be made before the big day arrives. One of the most important decisions you will make is selecting a venue for your wedding ceremony and reception. The venue will be one of the most memorable decisions you make, so it&#8217;s worth taking to find the right one for you and your partner. In this blog post we&#8217;ll explore 11 tips and tricks for finding a perfect location! #1 Find Out if Your Date is Available &#8211; As you&#8217;re shopping for wedding venues, it&#8217;s important to have a date in mind for your wedding. So as you&#8217;re reaching out to potential wedding venues make sure to ask if your date is available. If you&#8217;re flexible on which day of the week to get married, you may consider doing it on a Friday or Sunday. Some venues provide discounted rental rates, so make sure to ask about our Friday and Sunday rates. #2 Schedule a Venue Tour &#8211; The best way to know if the venue is right for you is to plan a visit with your partner. Before the tour, write down any questions you may have, and plan some time during your visit to review them with the venue. Also as you tour the venue, make sure to keep an open mind. It&#8217;s possible the venue may not be decorated, so try to visualize it dressed to the nine&#8217;s with all your wedding day decor. #3 Take Pictures and Video &#8211; During your tour, make sure to take pictures and video of the venue and decide the best location for perfect wedding and engagement photoshoot . You can always refer to them during the w"
    },
    {
      "id": "page-598c4067",
      "url": "https://promise-farm.com/blog/built-for-love-not-livestock-the-advantage-of-choosing-a-purpose-built-barn-venue",
      "title": "Built for Love, Not Livestock: The Advantage of Choosing a Purpose-Built Barn Venue | Promise Farm Wedding Venue",
      "description": "When choosing a barn venue for your wedding, do you want a barn that was built for events or one that was repurposed? Learn the difference.",
      "importance": "critical",
      "category": "venue",
      "lastCrawled": "2026-02-21T19:31:29.008Z",
      "contentHash": "069d70b6a7dc",
      "extractedFacts": [],
      "embeddingId": null,
      "imageUrls": [
        "https://promise-farm.com/wp-content/uploads/2025/09/logo.png",
        "https://promise-farm.com/wp-content/uploads/2025/10/Promise-Farm-529.jpg"
      ],
      "textSample": "Built for Love, Not Livestock: The Advantage of Choosing a Purpose-Built Barn Venue | Promise Farm Wedding Venue Home Weddings Events Gallery Reviews FAQs More Nearby Lodging Preferred Vendors Blog Contact Schedule a Tour Built for Love, Not Livestock: The Advantage of Choosing a Purpose-Built Barn Venue Home Blog Built for Love, Not Livestock: The Advantage of Choosing a Purpose-Built Barn Venue When couples picture a barn wedding , they often imagine warm wood beams, romantic string lights, and that magical blend of rustic charm and elegant celebration. But not all barns are created equal. While many venues start as old farm buildings repurposed for weddings, Promise Farm was built from the ground up for weddings and events, combining the authentic look and feel of a classic barn with all the modern comforts today’s couples and guests deserve. Designed with Your Day in Mind A repurposed barn may have history, but it wasn’t built with weddings in mind. That can mean awkward layouts, limited power sources for entertainment, or inconvenient spaces for catering, restrooms, or guests with mobility needs. Promise Farm, on the other hand, was purposefully designed for flawless celebrations. Every detail from the spacious bridal and groom suites to the climate-controlled event space and built-in lighting was created to make your wedding day flow effortlessly. There’s no need to “make it work” in a space that was never meant for events. Here, everything simply works beautifully. Modern Comfort Meets Rustic Beauty At Promise Farm, couples don’t have to choose between the rustic aesthetic they love and the comfort their guests expect. The barn features soaring wood beams, natural textures, and open-air charm, yet every inch is thoughtfully equipped with modern amenities, including heating and cooling, accessible restrooms, and a high-quality sound system. You’ll enjoy all the ambiance of a countryside barn wedding without worrying about muddy floors, lack of AC, or makeshift"
    },
    {
      "id": "page-bbc720be",
      "url": "https://promise-farm.com/blog/how-to-schedule-your-wedding-timeline-in-four-easy-steps",
      "title": "How to Schedule Your Wedding Timeline in Four Easy Steps",
      "description": "Schedule your wedding timeline in four easy steps. Plan the ceremony, reception, and photography for a seamless day at Promise Farm.",
      "importance": "medium",
      "category": "blog",
      "lastCrawled": "2026-02-21T19:31:29.010Z",
      "contentHash": "19fab9c943dc",
      "extractedFacts": [],
      "embeddingId": null,
      "imageUrls": [
        "https://promise-farm.com/wp-content/uploads/2025/09/logo.png",
        "https://promise-farm.com/wp-content/uploads/2021/09/weddingvenuelancasterpa2.jpg"
      ],
      "textSample": "How to Schedule Your Wedding Timeline in Four Easy Steps Home Weddings Events Gallery Reviews FAQs More Nearby Lodging Preferred Vendors Blog Contact Schedule a Tour How to Schedule Your Wedding Timeline in Four Easy Steps Home Blog How to Schedule Your Wedding Timeline in Four Easy Steps Planning a wedding involves countless details, but one of the most important aspects to get right is your wedding timeline. A well-structured timeline ensures that your big day flows smoothly, allowing you and your guests to enjoy every moment without stress. At Promise Farm, we understand the importance of a seamless wedding day, and we're here to help you create a timeline that works perfectly for your unique celebration. In this blog post, we'll walk you through four easy steps to schedule your wedding timeline, ensuring that your day is as memorable as it is organized. Step 1: Start with the Ceremony The ceremony is the centerpiece of your wedding day, and it’s where your timeline should begin. The timing of your ceremony will influence the rest of the day's schedule, so it’s important to choose a time that fits your overall vision. Key Considerations for Scheduling the Ceremony: Time of Day: Decide whether you want a morning, afternoon, or evening ceremony. Each option has its benefits; for example, a late afternoon ceremony can lead directly into an evening reception without a long break. Duration: Typically, wedding ceremonies last between 30 minutes to an hour, depending on the format and any religious or cultural traditions. Sunset and Lighting: If you’re planning an outdoor ceremony at Promise Farm, consider the timing of sunset, especially if you want to capture beautiful golden-hour photos. Starting your timeline with the ceremony helps anchor the rest of the day’s events. For more tips on planning your ceremony at our venue, check out our wedding planning guide . Step 2: Plan the Reception Events Once you’ve established the ceremony time, it’s time to plan the sequence"
    },
    {
      "id": "page-911456f2",
      "url": "https://promise-farm.com/blog/best-barn-wedding-venue-lancaster",
      "title": "Best Barn Wedding Venue in Lancaster | Promise Farm PA",
      "description": "Celebrate your big day at Promise Farm, a barn wedding venue in Lancaster with scenic views, rustic charm, flexible vendors, & affordable wedding packages.",
      "importance": "critical",
      "category": "venue",
      "lastCrawled": "2026-02-21T19:31:29.011Z",
      "contentHash": "30204a4cc711",
      "extractedFacts": [],
      "embeddingId": null,
      "imageUrls": [
        "https://promise-farm.com/wp-content/uploads/2025/09/logo.png",
        "https://promise-farm.com/wp-content/uploads/2022/10/addie_eshelman_bdw-731_websize.jpg"
      ],
      "textSample": "Best Barn Wedding Venue in Lancaster | Promise Farm PA Home Weddings Events Gallery Reviews FAQs More Nearby Lodging Preferred Vendors Blog Contact Schedule a Tour What Makes Promise Farm a Top Choice for Couples Seeking a Barn Wedding in Lancaster? Home Blog What Makes Promise Farm a Top Choice for Couples Seeking a Barn Wedding in Lancaster? When it comes to getting married in Lancaster, PA, Promise Farm is one of the best options for couples who want a rustic, unforgettable wedding. This venue offers a stunning location with beautiful countryside views, a gorgeous rustic barn, and peaceful surroundings. It is perfect for couples who want a serene, natural setting for their big day. The venue’s natural beauty creates the perfect backdrop for both breathtaking photos and a memorable celebration. Promise Farm has everything you need for a special wedding, with plenty of space to make your dreams come true, whether you want a small, private ceremony or a big party. Why Promise Farm Is the Perfect Lancaster Barn Wedding Venue Promise Farm offers all the right ingredients for a memorable wedding day. Located in Lancaster County, this picturesque barn wedding venue stands out for its natural beauty and flexible options, making it a top choice for couples who are planning their wedding. With its combination of rustic charm and modern amenities, Promise Farm ensures that every couple can create a wedding that perfectly reflects their style and preferences. A Beautiful Barn Surrounded by Nature Promise Farm features a stunning barn that blends rustic charm with modern comfort. This barn is spacious enough for your guests to feel comfortable while adding a warm, inviting atmosphere to your wedding day. The barn is perfect for both ceremonies and receptions, and the surrounding 55 acres of countryside with a pond and fountain make for a tranquil and beautiful backdrop for your wedding photos. Promise Farm is a great place to get married any time of year, from spring to winte"
    },
    {
      "id": "page-cd9c512a",
      "url": "https://promise-farm.com/wp-json/wp/v2/pages/26",
      "title": "",
      "description": "",
      "importance": "medium",
      "category": "other",
      "lastCrawled": "2026-02-21T19:31:29.012Z",
      "contentHash": "d41d8cd98f00",
      "extractedFacts": [],
      "embeddingId": null,
      "imageUrls": [],
      "textSample": ""
    },
    {
      "id": "page-fd4208d0",
      "url": "https://promise-farm.com/wp-json/wp/v2/pages/30",
      "title": "",
      "description": "",
      "importance": "medium",
      "category": "other",
      "lastCrawled": "2026-02-21T19:31:29.014Z",
      "contentHash": "d41d8cd98f00",
      "extractedFacts": [],
      "embeddingId": null,
      "imageUrls": [],
      "textSample": ""
    },
    {
      "id": "page-9e5e584a",
      "url": "https://promise-farm.com/wp-json/wp/v2/pages/28",
      "title": "",
      "description": "",
      "importance": "medium",
      "category": "other",
      "lastCrawled": "2026-02-21T19:31:29.015Z",
      "contentHash": "d41d8cd98f00",
      "extractedFacts": [],
      "embeddingId": null,
      "imageUrls": [],
      "textSample": ""
    },
    {
      "id": "page-24dd85dc",
      "url": "https://promise-farm.com/wp-json/wp/v2/pages/36",
      "title": "",
      "description": "",
      "importance": "medium",
      "category": "other",
      "lastCrawled": "2026-02-21T19:31:29.017Z",
      "contentHash": "d41d8cd98f00",
      "extractedFacts": [],
      "embeddingId": null,
      "imageUrls": [],
      "textSample": ""
    },
    {
      "id": "page-c52a829d",
      "url": "https://promise-farm.com/wp-json/wp/v2/pages/31",
      "title": "",
      "description": "",
      "importance": "medium",
      "category": "other",
      "lastCrawled": "2026-02-21T19:31:29.018Z",
      "contentHash": "d41d8cd98f00",
      "extractedFacts": [],
      "embeddingId": null,
      "imageUrls": [],
      "textSample": ""
    },
    {
      "id": "page-5687fbe9",
      "url": "https://promise-farm.com/wp-json/wp/v2/pages/34",
      "title": "",
      "description": "",
      "importance": "medium",
      "category": "other",
      "lastCrawled": "2026-02-21T19:31:29.020Z",
      "contentHash": "d41d8cd98f00",
      "extractedFacts": [],
      "embeddingId": null,
      "imageUrls": [],
      "textSample": ""
    },
    {
      "id": "page-96e23321",
      "url": "https://promise-farm.com/wp-json/wp/v2/pages/33",
      "title": "",
      "description": "",
      "importance": "medium",
      "category": "other",
      "lastCrawled": "2026-02-21T19:31:29.021Z",
      "contentHash": "d41d8cd98f00",
      "extractedFacts": [],
      "embeddingId": null,
      "imageUrls": [],
      "textSample": ""
    },
    {
      "id": "page-26b8965d",
      "url": "https://promise-farm.com/cdn-cgi/l/email-protection",
      "title": "Email Protection | Cloudflare",
      "description": "",
      "importance": "medium",
      "category": "other",
      "lastCrawled": "2026-02-21T19:31:29.022Z",
      "contentHash": "4ba7e83e6d87",
      "extractedFacts": [],
      "embeddingId": null,
      "imageUrls": [],
      "textSample": "Email Protection | Cloudflare Please enable cookies. Email Protection You are unable to access this email address promise-farm.com The website from which you got to this page is protected by Cloudflare. Email addresses on that page have been hidden in order to keep them from being accessed by malicious bots. You must enable Javascript in your browser in order to decode the e-mail address . If you have a website and are interested in protecting it in a similar way, you can sign up for Cloudflare . How does Cloudflare protect email addresses on website from spammers? Can I sign up for Cloudflare? Cloudflare Ray ID: 9d18aa09ff92c3f8 &bull; Your IP: Click to reveal 172.56.219.13 &bull; Performance & security by Cloudflare"
    }
  ]
}
